pyxdr/__init__.py
pyxdr/client.py
pyxdr/const.py
pyxdr/error.py
pyxdr/pyxdr.py
pyxdr-1.0.1.dist-info/licenses/LICENSE
pyxdr-1.0.1.dist-info/METADATA
pyxdr-1.0.1.dist-info/WHEEL
pyxdr-1.0.1.dist-info/top_level.txt
pyxdr-1.0.1.dist-info/RECORD
